package_aumentosalario/__init__.py
package_aumentosalario/file1_name.py
package_aumentosalario/file2_name.py
package_aumentosalario-0.0.1.dist-info/METADATA
package_aumentosalario-0.0.1.dist-info/WHEEL
package_aumentosalario-0.0.1.dist-info/top_level.txt
package_aumentosalario-0.0.1.dist-info/RECORD
