Metadata-Version: 2.1
Name: package-aumentosalario
Version: 0.0.1
Summary: My short description
Home-page: https://github.com/TarsilaNascMartins/desafio-simple-package-template
Author: Tarsila Martins
Author-email: tarsilawho@gmail.com
Requires-Python: >=3.8
